hubspot_article_translator/__init__.py
hubspot_article_translator/core.py
hubspot_article_translator/translation/__init__.py
hubspot_article_translator/translation/manager.py
hubspot_article_translator/translation/clients/__init__.py
hubspot_article_translator/translation/clients/aws.py
hubspot_article_translator/translation/clients/azure.py
hubspot_article_translator/translation/clients/base.py
hubspot_article_translator/translation/content_languages/__init__.py
hubspot_article_translator/translation/helpers/__init__.py
hubspot_article_translator-0.1.1.dist-info/LICENSE
hubspot_article_translator-0.1.1.dist-info/METADATA
hubspot_article_translator-0.1.1.dist-info/WHEEL
hubspot_article_translator-0.1.1.dist-info/top_level.txt
hubspot_article_translator-0.1.1.dist-info/RECORD
