Metadata-Version: 2.1
Name: hubspot-article-translator
Version: 0.1.1
Summary: Translating Hubspot Articles
Author: mattcoulter7 (Matt Coulter)
Author-email: <mattcoul7@gmail.com>
Keywords: python,hubspot,translation,knowledgebase,articles
Classifier: Development Status :: 1 - Planning
Classifier: Intended Audience :: Developers
Classifier: Programming Language :: Python :: 3
Classifier: Operating System :: Unix
Classifier: Operating System :: MacOS :: MacOS X
Classifier: Operating System :: Microsoft :: Windows
License-File: LICENSE
